clipp/__init__.py
clipp/core.py
clipp/utils.py
clipp-1.3.2.dist-info/LICENSE
clipp-1.3.2.dist-info/METADATA
clipp-1.3.2.dist-info/WHEEL
clipp-1.3.2.dist-info/top_level.txt
clipp-1.3.2.dist-info/RECORD
