Metadata-Version: 2.1
Name: clipp
Version: 1.3.2
Summary: A POSIX-compliant CLI parser.
Author: Ben Ohling
License: GNU GENERAL PUBLIC LICENSE
Requires-Python: >=3.11
License-File: LICENSE
Provides-Extra: dev
Requires-Dist: pydata-sphinx-theme ; extra == 'dev'
Requires-Dist: pytest ; extra == 'dev'
Requires-Dist: sphinx ; extra == 'dev'
